pynans/__init__.py
pynans/pynans.py
pynans-0.1.0.dist-info/LICENSE.txt
pynans-0.1.0.dist-info/METADATA
pynans-0.1.0.dist-info/WHEEL
pynans-0.1.0.dist-info/RECORD
