Metadata-Version: 2.3
Name: pynans
Version: 0.1.0
Summary: Investment library for Python
License: MIT
Keywords: pynans,fastapi,python,finance,investment
Author: Naga Sanka
Author-email: nsanka@me.com
Maintainer: Naga Sanka
Maintainer-email: nsanka@me.com
Requires-Python: >=3.10
Classifier: Development Status :: 2 - Pre-Alpha
Classifier: Programming Language :: Python
Classifier: License :: OSI Approved :: MIT License
Classifier: Operating System :: OS Independent
Provides-Extra: dev
Provides-Extra: text
Requires-Dist: black ; extra == "dev"
Requires-Dist: fastapi[all] ; extra == "text"
Requires-Dist: matplotlib (>=3.10.1,<4.0.0)
Requires-Dist: mypy ; extra == "dev"
Requires-Dist: pandas (>=2.2.3,<3.0.0)
Requires-Dist: pre-commit ; extra == "dev"
Requires-Dist: pytest ; extra == "dev"
Requires-Dist: yfinance (>=0.2.56,<0.3.0)
Project-URL: Documentation, https://pynans.readthedocs.io/en/latest/
Project-URL: Homepage, https://pynans.com
Project-URL: Repository, https://github.com/nsanka/pynans
